{
  "modules": {
    "byIdentifier": {
      "external \"react\"": 0,
      "external \"@babel/runtime/regenerator\"": 1,
      "external \"next/head\"": 2,
      "external \"isomorphic-unfetch\"": 3,
      "external \"next/link\"": 4,
      "multi ./pages/index.js": 5,
      "multi ./pages/post.js": 6,
      "node_modules/next/dist/build/webpack/loaders/next-babel-loader.js??ref--4!pages/post.js": 7,
      "multi node_modules/next/dist/pages/_app.js": 8,
      "node_modules/next/dist/pages/_app.js": 9,
      "external \"next/app\"": 10,
      "multi node_modules/next/dist/pages/_error.js": 11,
      "node_modules/next/dist/pages/_error.js": 12,
      "external \"next/error\"": 13,
      "multi node_modules/next/dist/pages/_document.js": 14,
      "node_modules/next/dist/pages/_document.js": 15,
      "external \"next/document\"": 16,
      "node_modules/next/dist/build/webpack/loaders/next-babel-loader.js??ref--4!pages/index.js 8752daef65930254b8d94519bfcaa21a": 17
    },
    "usedIds": {
      "0": 0,
      "1": 1,
      "2": 2,
      "3": 3,
      "4": 4,
      "5": 5,
      "6": 6,
      "7": 7,
      "8": 8,
      "9": 9,
      "10": 10,
      "11": 11,
      "12": 12,
      "13": 13,
      "14": 14,
      "15": 15,
      "16": 16,
      "17": 17
    }
  },
  "chunks": {
    "byName": {
      "static\\JgWXXaIDwEWDq8dEE8~Dm\\pages\\index.js": 0,
      "static\\JgWXXaIDwEWDq8dEE8~Dm\\pages\\post.js": 1,
      "static\\JgWXXaIDwEWDq8dEE8~Dm\\pages\\_app.js": 2,
      "static\\JgWXXaIDwEWDq8dEE8~Dm\\pages\\_error.js": 3,
      "static\\JgWXXaIDwEWDq8dEE8~Dm\\pages\\_document.js": 4,
      "static\\oRY7rXlgwgVtLdl5KKPfS\\pages\\index.js": 5,
      "static\\oRY7rXlgwgVtLdl5KKPfS\\pages\\post.js": 6,
      "static\\oRY7rXlgwgVtLdl5KKPfS\\pages\\_app.js": 7,
      "static\\oRY7rXlgwgVtLdl5KKPfS\\pages\\_error.js": 8,
      "static\\oRY7rXlgwgVtLdl5KKPfS\\pages\\_document.js": 9,
      "static\\IwIi4BK8JdVnAgocsJIck\\pages\\index.js": 0,
      "static\\IwIi4BK8JdVnAgocsJIck\\pages\\post.js": 1,
      "static\\IwIi4BK8JdVnAgocsJIck\\pages\\_app.js": 2,
      "static\\IwIi4BK8JdVnAgocsJIck\\pages\\_error.js": 3,
      "static\\IwIi4BK8JdVnAgocsJIck\\pages\\_document.js": 4,
      "static\\BVvoEBG_uDahxCilXrJla\\pages\\index.js": 5,
      "static\\BVvoEBG_uDahxCilXrJla\\pages\\post.js": 6,
      "static\\BVvoEBG_uDahxCilXrJla\\pages\\_app.js": 7,
      "static\\BVvoEBG_uDahxCilXrJla\\pages\\_error.js": 8,
      "static\\BVvoEBG_uDahxCilXrJla\\pages\\_document.js": 9
    },
    "bySource": {},
    "usedIds": [
      5,
      6,
      7,
      8,
      9
    ]
  }
}